fastapi_orm/__init__.py
fastapi_orm/__main__.py
fastapi_orm/abstract.py
fastapi_orm/advanced_constraints.py
fastapi_orm/aggregations.py
fastapi_orm/audit.py
fastapi_orm/cache.py
fastapi_orm/cli.py
fastapi_orm/composite_keys.py
fastapi_orm/constraints.py
fastapi_orm/database.py
fastapi_orm/distributed_cache.py
fastapi_orm/exceptions.py
fastapi_orm/factories.py
fastapi_orm/fields.py
fastapi_orm/file_upload.py
fastapi_orm/fulltext.py
fastapi_orm/graphql_integration.py
fastapi_orm/hooks.py
fastapi_orm/indexes.py
fastapi_orm/json_ops.py
fastapi_orm/middleware.py
fastapi_orm/migration_tools.py
fastapi_orm/migrations.py
fastapi_orm/mixins.py
fastapi_orm/model.py
fastapi_orm/monitoring.py
fastapi_orm/performance.py
fastapi_orm/polymorphic.py
fastapi_orm/pool_management.py
fastapi_orm/pool_monitoring.py
fastapi_orm/query.py
fastapi_orm/query_builder.py
fastapi_orm/rate_limit.py
fastapi_orm/read_replicas.py
fastapi_orm/relations.py
fastapi_orm/resilience.py
fastapi_orm/seeding.py
fastapi_orm/streaming.py
fastapi_orm/tenancy.py
fastapi_orm/testing.py
fastapi_orm/transactions.py
fastapi_orm/utils.py
fastapi_orm/validators.py
fastapi_orm/views.py
fastapi_orm/websocket.py
fastapi_orm-0.11.0.dist-info/licenses/LICENSE
fastapi_orm-0.11.0.dist-info/METADATA
fastapi_orm-0.11.0.dist-info/WHEEL
fastapi_orm-0.11.0.dist-info/top_level.txt
fastapi_orm-0.11.0.dist-info/RECORD
