Metadata-Version: 2.4
Name: fastapi-orm
Version: 0.11.0
Summary: A production-ready ORM for FastAPI with async support, automatic Pydantic integration, and Django-like syntax
Home-page: https://github.com/Alqudimi/FastApiOrm
Author: Abdulaziz Al-Qadimi
Author-email: eng7mi@gmail.com
Project-URL: Bug Tracker, https://github.com/Alqudimi/FastApiOrm/issues
Project-URL: Documentation, https://github.com/Alqudimi/FastApiOrm/tree/main/doc
Project-URL: Source Code, https://github.com/Alqudimi/FastApiOrm
Project-URL: Changelog, https://github.com/Alqudimi/FastApiOrm/blob/main/CHANGELOG_V0.11.md
Keywords: fastapi,orm,sqlalchemy,async,pydantic,database,postgresql,mysql,sqlite,rest-api,crud,asyncio,multi-tenancy,audit-logging,caching,websockets
Classifier: Development Status :: 4 - Beta
Classifier: Intended Audience :: Developers
Classifier: Topic :: Software Development :: Libraries :: Python Modules
Classifier: Topic :: Database
Classifier: Topic :: Internet :: WWW/HTTP
Classifier: License :: OSI Approved :: MIT License
Classifier: Programming Language :: Python :: 3
Classifier: Programming Language :: Python :: 3.11
Classifier: Programming Language :: Python :: 3.12
Classifier: Framework :: FastAPI
Classifier: Framework :: AsyncIO
Classifier: Operating System :: OS Independent
Classifier: Typing :: Typed
Requires-Python: >=3.11
License-File: LICENSE
Requires-Dist: sqlalchemy>=2.0.0
Requires-Dist: fastapi>=0.100.0
Requires-Dist: pydantic>=2.0.0
Requires-Dist: uvicorn>=0.20.0
Requires-Dist: asyncpg>=0.29.0
Requires-Dist: aiosqlite>=0.19.0
Requires-Dist: alembic>=1.12.0
Requires-Dist: aiosqlite
Requires-Dist: alembic
Requires-Dist: asyncpg
Requires-Dist: fastapi
Requires-Dist: pydantic
Requires-Dist: sqlalchemy
Requires-Dist: uvicorn
Requires-Dist: httpx
Requires-Dist: pytest
Requires-Dist: pytest-asyncio
Requires-Dist: httpx
Requires-Dist: pytest
Requires-Dist: pytest-asyncio
Requires-Dist: httpx
Requires-Dist: pytest
Requires-Dist: pytest-asyncio
Requires-Dist: aiosqlite
Requires-Dist: alembic
Requires-Dist: asyncpg
Requires-Dist: fastapi
Requires-Dist: httpx
Requires-Dist: pydantic
Requires-Dist: pytest
Requires-Dist: pytest-asyncio
Requires-Dist: sqlalchemy
Requires-Dist: uvicorn
Requires-Dist: aiosqlite
Requires-Dist: alembic
Requires-Dist: asyncpg
Requires-Dist: fastapi
Requires-Dist: httpx
Requires-Dist: pydantic
Requires-Dist: pytest
Requires-Dist: pytest-asyncio
Requires-Dist: sqlalchemy
Requires-Dist: uvicorn
Requires-Dist: aiosqlite
Requires-Dist: alembic
Requires-Dist: asyncpg
Requires-Dist: fastapi
Requires-Dist: httpx
Requires-Dist: pydantic
Requires-Dist: pytest
Requires-Dist: pytest-asyncio
Requires-Dist: sqlalchemy
Requires-Dist: uvicorn
Requires-Dist: aiosqlite
Requires-Dist: alembic
Requires-Dist: asyncpg
Requires-Dist: fastapi
Requires-Dist: httpx
Requires-Dist: pydantic
Requires-Dist: pytest
Requires-Dist: pytest-asyncio
Requires-Dist: sqlalchemy
Requires-Dist: uvicorn
Requires-Dist: aiosqlite
Requires-Dist: alembic
Requires-Dist: asyncpg
Requires-Dist: fastapi
Requires-Dist: httpx
Requires-Dist: pydantic
Requires-Dist: pytest
Requires-Dist: pytest-asyncio
Requires-Dist: sqlalchemy
Requires-Dist: uvicorn
Requires-Dist: aiosqlite
Requires-Dist: alembic
Requires-Dist: asyncpg
Requires-Dist: fastapi
Requires-Dist: httpx
Requires-Dist: pydantic
Requires-Dist: pytest
Requires-Dist: pytest-asyncio
Requires-Dist: sqlalchemy
Requires-Dist: uvicorn
Requires-Dist: aiosqlite
Requires-Dist: alembic
Requires-Dist: asyncpg
Requires-Dist: fastapi
Requires-Dist: httpx
Requires-Dist: pydantic
Requires-Dist: pytest
Requires-Dist: pytest-asyncio
Requires-Dist: sqlalchemy
Requires-Dist: uvicorn
Provides-Extra: redis
Requires-Dist: redis>=5.0.0; extra == "redis"
Provides-Extra: websockets
Requires-Dist: websockets>=12.0; extra == "websockets"
Provides-Extra: graphql
Requires-Dist: strawberry-graphql>=0.200.0; extra == "graphql"
Provides-Extra: files
Requires-Dist: aiofiles>=23.0.0; extra == "files"
Requires-Dist: boto3>=1.28.0; extra == "files"
Requires-Dist: pillow>=10.0.0; extra == "files"
Provides-Extra: dev
Requires-Dist: pytest>=7.4.0; extra == "dev"
Requires-Dist: pytest-asyncio>=0.21.0; extra == "dev"
Requires-Dist: httpx>=0.24.0; extra == "dev"
Provides-Extra: all
Requires-Dist: redis>=5.0.0; extra == "all"
Requires-Dist: websockets>=12.0; extra == "all"
Requires-Dist: strawberry-graphql>=0.200.0; extra == "all"
Requires-Dist: aiofiles>=23.0.0; extra == "all"
Requires-Dist: boto3>=1.28.0; extra == "all"
Requires-Dist: pillow>=10.0.0; extra == "all"
Dynamic: author
Dynamic: author-email
Dynamic: classifier
Dynamic: description
Dynamic: description-content-type
Dynamic: home-page
Dynamic: keywords
Dynamic: license-file
Dynamic: project-url
Dynamic: provides-extra
Dynamic: requires-dist
Dynamic: requires-python
Dynamic: summary
